ownership/__init__.py
ownership/py.typed
ownership-0.0.1.dist-info/METADATA
ownership-0.0.1.dist-info/WHEEL
ownership-0.0.1.dist-info/licenses/LICENSE
ownership-0.0.1.dist-info/RECORD
